{
    "_id": "58fd9554e7416f96efac8009",
    "isActive": true,
    "lastLogin": "Monday, March 23, 2015 10:28 AM",
    "balance": "$1,055.58",
    "age": 32,
    "eyeColor": "blue",
    "name": {
        "title": "MRS",
        "first": "Cooper",
        "last": "Ferguson"
    },
    "company": "JIMBIES",
    "email": "cooper.ferguson@jimbies.ca",
    "phone": [
        {
            "_id": "58fd95542515f242c165a46f",
            "num": "+1 (875) 400-3124",
            "type": "work"
        }
    ],
    "address": {
        "_id": "58fd955449bbb8de76c9f304",
        "num": 916,
        "street": "Wyckoff Street",
        "city": "Bloomington",
        "state": "Virgin Islands",
        "zip": 5179,
        "latitude": "16.164194",
        "longitude": "7.71184"
    },
    "bio": "Magna enim id pariatur ipsum occaecat id officia consectetur incididunt Lorem duis officia ullamco nisi. Adipisicing fugiat excepteur qui reprehenderit occaecat in sit ullamco. Proident cillum duis exercitation voluptate veniam irure exercitation. Esse culpa duis incididunt ut et culpa sunt sint laborum sit excepteur proident eu ipsum. Dolore esse sit est sit culpa quis veniam. Occaecat non in Lorem esse cillum duis ullamco sint ipsum dolor cupidatat duis pariatur pariatur. Anim Lorem laboris qui eu fugiat nisi eiusmod labore pariatur quis irure sunt Lorem.",
    "tags": [
        "labore"
    ],
    "friends": [],
    "greeting": "Hello, Cooper! You have 5 unread messages.",
    "friend": [
        {
            "_id": "58fd95546af510cff64eac8f"
        },
        {
            "_id": "58fd92fedc595c7f63b638ef"
        },
        {
            "_id": "58fd92fe4744b9ee1b9e125e"
        },
        {
            "_id": "58fd9554b7297ccb3d801a4e"
        },
        {
            "_id": "58fd92ffa6caa3f4d4b7ebc4"
        }
    ]
}