{
    "_id": "5903f919aae958c2e0457184",
    "isActive": false,
    "lastLogin": "Monday, February 22, 2016 10:25 AM",
    "balance": "$1,448.21",
    "dob": "2014/06/24",
    "eyeColor": "green",
    "name": {
        "title": "MISS",
        "first": "Cantrell",
        "last": "Gaines"
    },
    "company": "ACRUEX",
    "email": "cantrell.gaines@acruex.io",
    "phone": [
        {
            "_id": "5903f9197d80c681cdfac10e",
            "num": "+1 (933) 582-3558",
            "type": "home"
        },
        {
            "_id": "5903f9196e0f58920fc984eb",
            "num": "+1 (984) 575-2365",
            "type": "work"
        },
        {
            "_id": "5903f9190321f01299254605",
            "num": "+1 (951) 479-3112",
            "type": "mobile"
        }
    ],
    "address": {
        "_id": "5903f9194d3b19cc04157e5a",
        "num": 562,
        "street": "Balfour Place",
        "city": "Madaket",
        "state": "Minnesota",
        "zip": 3807,
        "latitude": "46.675228",
        "longitude": "56.93065"
    },
    "bio": "Id deserunt id mollit exercitation anim duis et id quis laboris anim sunt et. Culpa minim aliqua aliqua exercitation eiusmod esse. Est est laborum consequat non nisi incididunt in proident deserunt ea anim sint.",
    "tags": [
        "enim",
        "aute",
        "do",
        "commodo",
        "laboris",
        "sit"
    ],
    "friends": [
        {
            "_id": "5903f9182f4051a0139585f2"
        },
        {
            "_id": "5903f91af7857a222b8ceb60"
        },
        {
            "_id": "5903f91baf0cf31323731bb7"
        },
        {
            "_id": "5903f919fe3c968268ca9fa4"
        },
        {
            "_id": "5903f91bac1aae6fad53696f"
        }
    ],
    "greeting": "Hello, Cantrell! You have 10 unread messages."
}